hierarchical_results/__init__.py
hierarchical_results/cli.py
hierarchical_results/hierarchical_results.py
hierarchical_results/logging.py
hierarchical_results-0.0.6.dist-info/LICENSE
hierarchical_results-0.0.6.dist-info/METADATA
hierarchical_results-0.0.6.dist-info/WHEEL
hierarchical_results-0.0.6.dist-info/entry_points.txt
hierarchical_results-0.0.6.dist-info/top_level.txt
hierarchical_results-0.0.6.dist-info/RECORD
