Metadata-Version: 2.1
Name: hierarchical-results
Version: 0.0.6
Summary: Hierarchical results
Home-page: https://github.com/ivargr/hierarchical_results
Author: Ivar Grytten
Author-email: ivargry@ifi.uio.no
License: MIT license
Keywords: hierarchical_results
Classifier: Development Status :: 2 - Pre-Alpha
Classifier: Intended Audience :: Developers
Classifier: License :: OSI Approved :: MIT License
Classifier: Natural Language :: English
Classifier: Programming Language :: Python :: 3
Classifier: Programming Language :: Python :: 3.6
Classifier: Programming Language :: Python :: 3.7
Classifier: Programming Language :: Python :: 3.8
Requires-Python: >=3.6
License-File: LICENSE
Requires-Dist: numpy
Requires-Dist: pandas
Requires-Dist: pathos
Requires-Dist: shared-memory-wrapper
